deeplin/EMA.py
deeplin/FGM.py
deeplin/__init__.py
deeplin/__main__.py
deeplin/inference.py
deeplin/inference_engine/__init__.py
deeplin/inference_engine/base.py
deeplin/inference_engine/hexin_engine.py
deeplin/inference_engine/hexin_server.py
deeplin/inference_engine/openai_engine.py
deeplin/inference_engine/vllm_engine.py
deeplin/random_util.py
deeplin/stack.py
deeplin/token_statistic.py
deeplin/torch_builder.py
deeplin-0.1.44.dist-info/LICENSE
deeplin-0.1.44.dist-info/METADATA
deeplin-0.1.44.dist-info/WHEEL
deeplin-0.1.44.dist-info/entry_points.txt
deeplin-0.1.44.dist-info/RECORD
