Metadata-Version: 2.3
Name: deeplin
Version: 0.1.44
Summary: deep learning toolbox for LinXueyuan
License: MIT
Author: LinXueyuanStdio
Author-email: 23211526+LinXueyuanStdio@users.noreply.github.com
Classifier: License :: OSI Approved :: MIT License
Classifier: Programming Language :: Python :: 2
Classifier: Programming Language :: Python :: 2.7
Classifier: Programming Language :: Python :: 3
Classifier: Programming Language :: Python :: 3.4
Classifier: Programming Language :: Python :: 3.5
Classifier: Programming Language :: Python :: 3.6
Classifier: Programming Language :: Python :: 3.7
Classifier: Programming Language :: Python :: 3.8
Classifier: Programming Language :: Python :: 3.9
Classifier: Programming Language :: Python :: 3.10
Classifier: Programming Language :: Python :: 3.11
Classifier: Programming Language :: Python :: 3.12
Classifier: Programming Language :: Python :: 3.13
Requires-Dist: fastapi
Requires-Dist: httpx
Requires-Dist: loguru
Requires-Dist: numpy
Requires-Dist: openai
Requires-Dist: pydantic
Requires-Dist: pytest
Requires-Dist: pytest-asyncio
Requires-Dist: python-dotenv
Requires-Dist: torch
Requires-Dist: transformers
Requires-Dist: uvicorn
Requires-Dist: xlin
